ape_titanoboa/__init__.py
ape_titanoboa/config.py
ape_titanoboa/provider.py
ape_titanoboa/py.typed
ape_titanoboa/trace.py
ape_titanoboa/transactions.py
ape_titanoboa/utils.py
ape_titanoboa/version.py
ape_titanoboa-0.8.0a1.dist-info/LICENSE
ape_titanoboa-0.8.0a1.dist-info/METADATA
ape_titanoboa-0.8.0a1.dist-info/WHEEL
ape_titanoboa-0.8.0a1.dist-info/top_level.txt
ape_titanoboa-0.8.0a1.dist-info/RECORD
