Metadata-Version: 2.2
Name: ape-titanoboa
Version: 0.8.0a1
Summary: ape-titanoboa: Titanoboa integration
Home-page: https://github.com/ApeWorX/ape-titanoboa
Author: ApeWorX Ltd.
Author-email: admin@apeworx.io
License: Apache-2.0
Keywords: ethereum
Classifier: Development Status :: 5 - Production/Stable
Classifier: Intended Audience :: Developers
Classifier: License :: OSI Approved :: Apache Software License
Classifier: Natural Language :: English
Classifier: Operating System :: MacOS
Classifier: Operating System :: POSIX
Classifier: Framework :: Pytest
Classifier: Programming Language :: Python :: 3
Classifier: Programming Language :: Python :: 3.10
Classifier: Programming Language :: Python :: 3.11
Classifier: Programming Language :: Python :: 3.12
Classifier: Programming Language :: Python :: 3.13
Requires-Python: >=3.9,<4
License-File: LICENSE
Requires-Dist: eth-ape<0.9,>=0.8.22
Requires-Dist: cchecksum<1,>=0.0.3
Requires-Dist: titanoboa<0.3,>=0.2.5
Requires-Dist: web3<8,>=7.6.1
Provides-Extra: test
Requires-Dist: pytest>=6.0; extra == "test"
Requires-Dist: pytest-xdist; extra == "test"
Requires-Dist: pytest-cov; extra == "test"
Requires-Dist: hypothesis<7.0,>=6.2.0; extra == "test"
Requires-Dist: ape-alchemy; extra == "test"
Requires-Dist: ape-etherscan; extra == "test"
Requires-Dist: ape-solidity; extra == "test"
Requires-Dist: ape-vyper<0.9,>=0.8.8; extra == "test"
Provides-Extra: lint
Requires-Dist: black>=24.10.0; extra == "lint"
Requires-Dist: mypy>=1.14.1; extra == "lint"
Requires-Dist: flake8<8,>=7.1.1; extra == "lint"
Requires-Dist: flake8-breakpoint<2,>=1.1.0; extra == "lint"
Requires-Dist: flake8-print<5,>=4.0.1; extra == "lint"
Requires-Dist: flake8-pydantic; extra == "lint"
Requires-Dist: flake8-type-checking; extra == "lint"
Requires-Dist: isort>=5.13.2; extra == "lint"
Requires-Dist: mdformat>=0.7.21; extra == "lint"
Requires-Dist: mdformat-gfm>=0.3.5; extra == "lint"
Requires-Dist: mdformat-frontmatter>=0.4.1; extra == "lint"
Requires-Dist: mdformat-pyproject>=0.0.2; extra == "lint"
Provides-Extra: release
Requires-Dist: setuptools>=75; extra == "release"
Requires-Dist: wheel; extra == "release"
Requires-Dist: twine; extra == "release"
Provides-Extra: dev
Requires-Dist: pytest>=6.0; extra == "dev"
Requires-Dist: pytest-xdist; extra == "dev"
Requires-Dist: pytest-cov; extra == "dev"
Requires-Dist: hypothesis<7.0,>=6.2.0; extra == "dev"
Requires-Dist: ape-alchemy; extra == "dev"
Requires-Dist: ape-etherscan; extra == "dev"
Requires-Dist: ape-solidity; extra == "dev"
Requires-Dist: ape-vyper<0.9,>=0.8.8; extra == "dev"
Requires-Dist: black>=24.10.0; extra == "dev"
Requires-Dist: mypy>=1.14.1; extra == "dev"
Requires-Dist: flake8<8,>=7.1.1; extra == "dev"
Requires-Dist: flake8-breakpoint<2,>=1.1.0; extra == "dev"
Requires-Dist: flake8-print<5,>=4.0.1; extra == "dev"
Requires-Dist: flake8-pydantic; extra == "dev"
Requires-Dist: flake8-type-checking; extra == "dev"
Requires-Dist: isort>=5.13.2; extra == "dev"
Requires-Dist: mdformat>=0.7.21; extra == "dev"
Requires-Dist: mdformat-gfm>=0.3.5; extra == "dev"
Requires-Dist: mdformat-frontmatter>=0.4.1; extra == "dev"
Requires-Dist: mdformat-pyproject>=0.0.2; extra == "dev"
Requires-Dist: setuptools>=75; extra == "dev"
Requires-Dist: wheel; extra == "dev"
Requires-Dist: twine; extra == "dev"
Requires-Dist: commitizen; extra == "dev"
Requires-Dist: pre-commit; extra == "dev"
Requires-Dist: pytest-watch; extra == "dev"
Requires-Dist: IPython; extra == "dev"
Requires-Dist: ipdb; extra == "dev"
Dynamic: author
Dynamic: author-email
Dynamic: classifier
Dynamic: description
Dynamic: description-content-type
Dynamic: home-page
Dynamic: keywords
Dynamic: license
Dynamic: provides-extra
Dynamic: requires-dist
Dynamic: requires-python
Dynamic: summary
